artworks.py
artworks-0.2.0.dist-info/LICENSE
artworks-0.2.0.dist-info/WHEEL
artworks-0.2.0.dist-info/METADATA
artworks-0.2.0.dist-info/RECORD
