Metadata-Version: 2.1
Name: artworks
Version: 0.2.0
Summary: 
Home-page: UNKNOWN
License: MIT
Author: castaneai
Author-email: castaneai@castaneai.net
Requires-Python: >=3.6,<4.0
Classifier: License :: OSI Approved :: MIT License
Classifier: Programming Language :: Python :: 3
Classifier: Programming Language :: Python :: 3.6
Classifier: Programming Language :: Python :: 3.7
Requires-Dist: mutagen (>=1.42,<2.0)
